parameterspace/__init__.py
parameterspace/base.py
parameterspace/condition.py
parameterspace/configspace_utils.py
parameterspace/parameters/__init__.py
parameterspace/parameters/base.py
parameterspace/parameters/categorical.py
parameterspace/parameters/continuous.py
parameterspace/parameters/integer.py
parameterspace/parameters/ordinal.py
parameterspace/parameterspace.py
parameterspace/priors/__init__.py
parameterspace/priors/base.py
parameterspace/priors/beta.py
parameterspace/priors/categorical.py
parameterspace/priors/truncated_normal.py
parameterspace/priors/uniform.py
parameterspace/py.typed
parameterspace/transformations/__init__.py
parameterspace/transformations/base.py
parameterspace/transformations/categorical.py
parameterspace/transformations/log_zero_one.py
parameterspace/transformations/zero_one.py
parameterspace/utils.py
parameterspace-0.10.2.dist-info/LICENSE
parameterspace-0.10.2.dist-info/METADATA
parameterspace-0.10.2.dist-info/NOTICE
parameterspace-0.10.2.dist-info/WHEEL
parameterspace-0.10.2.dist-info/RECORD
