Metadata-Version: 2.3
Name: parameterspace
Version: 0.10.2
Summary: Parametrized hierarchical spaces with flexible priors and transformations.
License: Apache-2.0
Author: Bosch Center for AI, Robert Bosch GmbH
Requires-Python: >=3.10,<4.0
Classifier: License :: OSI Approved :: Apache Software License
Classifier: Programming Language :: Python :: 3
Classifier: Programming Language :: Python :: 3.10
Classifier: Programming Language :: Python :: 3.11
Classifier: Programming Language :: Python :: 3.12
Classifier: Programming Language :: Python :: 3.13
Provides-Extra: examples
Requires-Dist: numpy (>=1.26.0)
Requires-Dist: scipy (>=1.14.0)
Project-URL: Repository, https://github.com/boschresearch/parameterspace
